xl_network/__init__.py
xl_network/mail.py
xl_network-1.0.0.dist-info/METADATA
xl_network-1.0.0.dist-info/WHEEL
xl_network-1.0.0.dist-info/licenses/LICENSE
xl_network-1.0.0.dist-info/RECORD
